pydarksky/__init__.py
pydarksky/darksky.py
pydarksky/weather.py
pydarksky-2.0.1.dist-info/DESCRIPTION.rst
pydarksky-2.0.1.dist-info/METADATA
pydarksky-2.0.1.dist-info/RECORD
pydarksky-2.0.1.dist-info/WHEEL
pydarksky-2.0.1.dist-info/metadata.json
pydarksky-2.0.1.dist-info/top_level.txt
