Metadata-Version: 2.0
Name: pydarksky
Version: 2.0.1
Summary: Python wrapper for darksky.net weather service
Home-page: https://github.com/PvtHaggard/pydarksky
Author: PvtHaggard
Author-email: pvthaggard@gmail.com
License: GPLv3
Platform: UNKNOWN
Requires-Dist: requests
